requests_oauthlib/__init__.py
requests_oauthlib/oauth1_auth.py
requests_oauthlib/oauth1_session.py
requests_oauthlib/oauth2_auth.py
requests_oauthlib/oauth2_session.py
requests_oauthlib/compliance_fixes/__init__.py
requests_oauthlib/compliance_fixes/douban.py
requests_oauthlib/compliance_fixes/facebook.py
requests_oauthlib/compliance_fixes/fitbit.py
requests_oauthlib/compliance_fixes/instagram.py
requests_oauthlib/compliance_fixes/linkedin.py
requests_oauthlib/compliance_fixes/mailchimp.py
requests_oauthlib/compliance_fixes/plentymarkets.py
requests_oauthlib/compliance_fixes/slack.py
requests_oauthlib/compliance_fixes/weibo.py
requests_oauthlib_activecampaign-1.3.1.dist-info/LICENSE
requests_oauthlib_activecampaign-1.3.1.dist-info/METADATA
requests_oauthlib_activecampaign-1.3.1.dist-info/WHEEL
requests_oauthlib_activecampaign-1.3.1.dist-info/top_level.txt
requests_oauthlib_activecampaign-1.3.1.dist-info/RECORD
