Metadata-Version: 2.1
Name: requests-oauthlib-activecampaign
Version: 1.3.1
Summary: A forked OAuthlib authentication support for Requests.
Home-page: https://github.com/requests/requests-oauthlib
Author: Kenneth Reitz
Author-email: me@kennethreitz.com
License: ISC
Platform: UNKNOWN
Classifier: Development Status :: 5 - Production/Stable
Classifier: Intended Audience :: Developers
Classifier: Natural Language :: English
Classifier: License :: OSI Approved :: BSD License
Classifier: Programming Language :: Python
Classifier: Programming Language :: Python :: 2
Classifier: Programming Language :: Python :: 2.7
Classifier: Programming Language :: Python :: 3
Classifier: Programming Language :: Python :: 3.4
Classifier: Programming Language :: Python :: 3.5
Classifier: Programming Language :: Python :: 3.6
Classifier: Programming Language :: Python :: 3.7
Classifier: Programming Language :: Python :: Implementation :: CPython
Classifier: Programming Language :: Python :: Implementation :: PyPy
Requires-Python: >=2.7, !=3.0.*, !=3.1.*, !=3.2.*, !=3.3.*
License-File: LICENSE
Requires-Dist: oauthlib-activecampaign (>=3.0.0)
Requires-Dist: requests (>=2.0.0)
Provides-Extra: rsa
Requires-Dist: oauthlib-activecampaign[signedtoken] (>=3.0.0) ; extra == 'rsa'
